django_microservice_admin/__init__.py
django_microservice_admin/admin.py
django_microservice_admin/apps.py
django_microservice_admin/jwt_serializer.py
django_microservice_admin/models.py
django_microservice_admin/tests.py
django_microservice_admin/urls.py
django_microservice_admin/views.py
django_microservice_admin/migrations/0001_initial.py
django_microservice_admin/migrations/0002_auto_20221011_1009.py
django_microservice_admin/migrations/0003_rename_redirect_url_adminapps_redirect_path.py
django_microservice_admin/migrations/0004_alter_adminapps_redirect_path.py
django_microservice_admin/migrations/0005_auto_20221019_1553.py
django_microservice_admin/migrations/0006_auto_20221019_1705.py
django_microservice_admin/migrations/__init__.py
django_microservice_admin/templates/admin/base.html
django_microservice_admin/templates/admin/base_site.html
django_microservice_admin/templates/admin/change_form.html
django_microservice_admin-0.1.7.dist-info/LICENSE
django_microservice_admin-0.1.7.dist-info/METADATA
django_microservice_admin-0.1.7.dist-info/WHEEL
django_microservice_admin-0.1.7.dist-info/top_level.txt
django_microservice_admin-0.1.7.dist-info/RECORD
